fastapi_kafka/__init__.py
fastapi_kafka/consumer.py
fastapi_kafka/schema.py
fastapi_kafka-0.1.5.dist-info/licenses/LICENSE
fastapi_kafka-0.1.5.dist-info/METADATA
fastapi_kafka-0.1.5.dist-info/WHEEL
fastapi_kafka-0.1.5.dist-info/top_level.txt
fastapi_kafka-0.1.5.dist-info/RECORD
