Metadata-Version: 2.4
Name: fastapi_kafka
Version: 0.1.5
Summary: A wrapper around FastAPI to easily consume kafka messages as routes
Author-email: OSS Mafia <dev@oss-mafia.com>
Project-URL: Homepage, https://github.com/OSSMafia/fastapi-kafka
Project-URL: Source, https://github.com/OSSMafia/fastapi-kafka
Keywords: fastapi,kafka,consumer,aiokafka
Classifier: Development Status :: 5 - Production/Stable
Classifier: Framework :: FastAPI
Classifier: Intended Audience :: Developers
Classifier: License :: OSI Approved :: MIT License
Classifier: Programming Language :: Python :: 3.9
Classifier: Programming Language :: Python :: 3.10
Classifier: Programming Language :: Python :: 3.11
Classifier: Programming Language :: Python :: 3.12
Requires-Python: >=3.9
License-File: LICENSE
Requires-Dist: fastapi>=0.95.0
Requires-Dist: aiokafka>=0.8.0
Dynamic: license-file
